pos3/__init__.py
pos3-0.2.1.dist-info/licenses/LICENSE
pos3-0.2.1.dist-info/METADATA
pos3-0.2.1.dist-info/WHEEL
pos3-0.2.1.dist-info/top_level.txt
pos3-0.2.1.dist-info/RECORD
