Metadata-Version: 2.4
Name: pos3
Version: 0.2.1
Summary: S3 Simple Sync - Make using S3 as simple as using local files
Author-email: Positronic Robotics <hi@positronic.ro>
License: Apache-2.0
Project-URL: Homepage, https://github.com/Positronic-Robotics/pos3
Project-URL: Repository, https://github.com/Positronic-Robotics/pos3
Classifier: Development Status :: 4 - Beta
Classifier: Intended Audience :: Developers
Classifier: License :: OSI Approved :: Apache Software License
Classifier: Programming Language :: Python :: 3
Requires-Python: >=3.9
License-File: LICENSE
Requires-Dist: boto3>=1.26.0
Requires-Dist: tqdm>=4.65.0
Provides-Extra: dev
Requires-Dist: pytest>=7.0; extra == "dev"
Requires-Dist: pytest-cov; extra == "dev"
Requires-Dist: ruff; extra == "dev"
Requires-Dist: pre-commit; extra == "dev"
Dynamic: license-file
